[
  {
    "handPile": [
      {
        "category": "Unite_word",
        "name": "Unite",
        "type": "gold",
        "isText": true
      },
      {
        "category": "Veggie",
        "name": "Veggie",
        "type": "gold",
        "isText": false
      },
      {
        "category": "Legends_word",
        "name": "Legends",
        "type": "gold",
        "isText": true
      },
      {
        "category": "Toolbox",
        "name": "Toolbox",
        "type": "gold",
        "isText": false
      },
      {
        "category": "Lie_word",
        "name": "Lie",
        "type": "gold",
        "isText": true
      },
      {
        "category": "Navigate_word",
        "name": "Navigate",
        "type": "gold",
        "isText": true
      }
    ],
    "config": {
      "maxSlots": 3,
      "penaltyTime": 3,
      "bingosNeeded": 2,
      "timeLimit": 100
    },
    "categoryTargets": {
      "Veggie": 3,
      "Legends_word": 5,
      "Unite_word": 3,
      "Navigate_word": 3,
      "Toolbox": 4,
      "Lie_word": 4
    },
    "cards": [
      {
        "row": 0,
        "card": {
          "category": "Injuries_word",
          "name": "Sprain",
          "type": "filler",
          "image": null,
          "isText": true
        },
        "layer": 1,
        "col": 0
      },
      {
        "row": 0,
        "card": {
          "category": "Fitness_word",
          "name": "Gym",
          "type": "filler",
          "image": null,
          "isText": true
        },
        "layer": 0,
        "col": 0
      },
      {
        "row": 0,
        "card": {
          "category": "Water_word",
          "name": "Yosemite",
          "type": "filler",
          "image": null,
          "isText": true
        },
        "layer": 1,
        "col": 1
      },
      {
        "row": 0,
        "card": {
          "category": "Fitness_word",
          "name": "Workout",
          "type": "filler",
          "image": null,
          "isText": true
        },
        "layer": 0,
        "col": 1
      },
      {
        "row": 0,
        "card": {
          "category": "Legends_word",
          "name": "Tale",
          "type": "regular",
          "image": null,
          "isText": true
        },
        "layer": 1,
        "col": 2
      },
      {
        "row": 0,
        "card": {
          "category": "Unite_word",
          "name": "Union",
          "type": "regular",
          "image": null,
          "isText": true
        },
        "layer": 0,
        "col": 2
      },
      {
        "row": 0,
        "card": {
          "category": "Toolbox",
          "name": "Adhesive tape",
          "type": "regular",
          "image": "res/Item/toolbox_adhesivetape_4.png",
          "isText": false
        },
        "layer": 1,
        "col": 3
      },
      {
        "row": 0,
        "card": {
          "category": "Veggie",
          "name": "Broccoli",
          "type": "regular",
          "image": "res/Item/veggie_broccoli_1.png",
          "isText": false
        },
        "layer": 0,
        "col": 3
      },
      {
        "row": 0,
        "card": {
          "category": "Shoes",
          "name": "Boots",
          "type": "filler",
          "image": "res/Item/shoes_boots_1.png",
          "isText": false
        },
        "layer": 1,
        "col": 4
      },
      {
        "row": 0,
        "card": {
          "category": "Wheel_word",
          "name": "Hubcap",
          "type": "filler",
          "image": null,
          "isText": true
        },
        "layer": 0,
        "col": 4
      },
      {
        "row": 1,
        "card": {
          "category": "Legends_word",
          "name": "Epic",
          "type": "regular",
          "image": null,
          "isText": true
        },
        "layer": 1,
        "col": 0
      },
      {
        "row": 1,
        "card": {
          "category": "Wheel_word",
          "name": "Axle",
          "type": "filler",
          "image": null,
          "isText": true
        },
        "layer": 0,
        "col": 0
      },
      {
        "row": 1,
        "card": {
          "category": "Water_word",
          "name": "Victoria",
          "type": "filler",
          "image": null,
          "isText": true
        },
        "layer": 1,
        "col": 1
      },
      {
        "row": 1,
        "card": {
          "category": "Injuries_word",
          "name": "Wound",
          "type": "filler",
          "image": null,
          "isText": true
        },
        "layer": 0,
        "col": 1
      },
      {
        "row": 1,
        "card": {
          "category": "Lie_word",
          "name": "Delude",
          "type": "regular",
          "image": null,
          "isText": true
        },
        "layer": 0,
        "col": 2
      },
      {
        "row": 1,
        "card": {
          "category": "Legends_word",
          "name": "Fable",
          "type": "regular",
          "image": null,
          "isText": true
        },
        "layer": 0,
        "col": 3
      },
      {
        "row": 1,
        "card": {
          "category": "Water_word",
          "name": "Havasu",
          "type": "filler",
          "image": null,
          "isText": true
        },
        "layer": 1,
        "col": 4
      },
      {
        "row": 1,
        "card": {
          "category": "Injuries_word",
          "name": "Bruise",
          "type": "filler",
          "image": null,
          "isText": true
        },
        "layer": 0,
        "col": 4
      },
      {
        "row": 2,
        "card": {
          "category": "Map",
          "name": "India",
          "type": "filler",
          "image": "res/Item/map_india_2.png",
          "isText": false
        },
        "layer": 1,
        "col": 0
      },
      {
        "row": 2,
        "card": {
          "category": "Pattern_word",
          "name": "Perseus",
          "type": "filler",
          "image": null,
          "isText": true
        },
        "layer": 0,
        "col": 0
      },
      {
        "row": 2,
        "card": {
          "category": "Fitness_word",
          "name": "Yoga",
          "type": "filler",
          "image": null,
          "isText": true
        },
        "layer": 1,
        "col": 1
      },
      {
        "row": 2,
        "card": {
          "category": "Flowers_word",
          "name": "Tulip",
          "type": "filler",
          "image": null,
          "isText": true
        },
        "layer": 0,
        "col": 1
      },
      {
        "row": 2,
        "card": {
          "category": "Navigate_word",
          "name": "Compass",
          "type": "regular",
          "image": null,
          "isText": true
        },
        "layer": 1,
        "col": 2
      },
      {
        "row": 2,
        "card": {
          "category": "Unite_word",
          "name": "League",
          "type": "regular",
          "image": null,
          "isText": true
        },
        "layer": 0,
        "col": 2
      },
      {
        "row": 2,
        "card": {
          "category": "Lie_word",
          "name": "Falsify",
          "type": "regular",
          "image": null,
          "isText": true
        },
        "layer": 0,
        "col": 3
      },
      {
        "row": 2,
        "card": {
          "category": "Shoes",
          "name": "Oxfords",
          "type": "filler",
          "image": "res/Item/shoes_oxfords_4.png",
          "isText": false
        },
        "layer": 1,
        "col": 4
      },
      {
        "row": 2,
        "card": {
          "category": "Flowers_word",
          "name": "Lily",
          "type": "filler",
          "image": null,
          "isText": true
        },
        "layer": 0,
        "col": 4
      },
      {
        "row": 3,
        "card": {
          "category": "Navigate_word",
          "name": "Sextant",
          "type": "regular",
          "image": null,
          "isText": true
        },
        "layer": 1,
        "col": 0
      },
      {
        "row": 3,
        "card": {
          "category": "Quest_word",
          "name": "Pursuit",
          "type": "filler",
          "image": null,
          "isText": true
        },
        "layer": 0,
        "col": 0
      },
      {
        "row": 3,
        "card": {
          "category": "Toolbox",
          "name": "Wrench",
          "type": "regular",
          "image": "res/Item/toolbox_wrench_2.png",
          "isText": false
        },
        "layer": 1,
        "col": 1
      },
      {
        "row": 3,
        "card": {
          "category": "Quest_word",
          "name": "Inquiry",
          "type": "filler",
          "image": null,
          "isText": true
        },
        "layer": 0,
        "col": 1
      },
      {
        "row": 3,
        "card": {
          "category": "Toolbox",
          "name": "Pliers",
          "type": "regular",
          "image": "res/Item/toolbox_pliers_1.png",
          "isText": false
        },
        "layer": 0,
        "col": 2
      },
      {
        "row": 3,
        "card": {
          "category": "Lie_word",
          "name": "Mislead",
          "type": "regular",
          "image": null,
          "isText": true
        },
        "layer": 1,
        "col": 3
      },
      {
        "row": 3,
        "card": {
          "category": "Veggie",
          "name": "Cabbage",
          "type": "regular",
          "image": "res/Item/veggie_cabbage_2.png",
          "isText": false
        },
        "layer": 0,
        "col": 3
      },
      {
        "row": 3,
        "card": {
          "category": "Legends_word",
          "name": "Myth",
          "type": "regular",
          "image": null,
          "isText": true
        },
        "layer": 0,
        "col": 4
      },
      {
        "row": 4,
        "card": {
          "category": "Lie_word",
          "name": "Deceive",
          "type": "regular",
          "image": null,
          "isText": true
        },
        "layer": 0,
        "col": 0
      },
      {
        "row": 4,
        "card": {
          "category": "Legends_word",
          "name": "Saga",
          "type": "regular",
          "image": null,
          "isText": true
        },
        "layer": 0,
        "col": 1
      },
      {
        "row": 4,
        "card": {
          "category": "Toolbox",
          "name": "Drill",
          "type": "regular",
          "image": "res/Item/toolbox_drill_3.png",
          "isText": false
        },
        "layer": 1,
        "col": 2
      },
      {
        "row": 4,
        "card": {
          "category": "Veggie",
          "name": "Potato",
          "type": "regular",
          "image": "res/Item/veggie_potato_3.png",
          "isText": false
        },
        "layer": 0,
        "col": 2
      },
      {
        "row": 4,
        "card": {
          "category": "Navigate_word",
          "name": "Signpost",
          "type": "regular",
          "image": null,
          "isText": true
        },
        "layer": 1,
        "col": 3
      },
      {
        "row": 4,
        "card": {
          "category": "Unite_word",
          "name": "Alliance",
          "type": "regular",
          "image": null,
          "isText": true
        },
        "layer": 0,
        "col": 3
      },
      {
        "row": 4,
        "card": {
          "category": "Fitness_word",
          "name": "Pilates",
          "type": "filler",
          "image": null,
          "isText": true
        },
        "layer": 0,
        "col": 4
      }
    ],
    "handDisplay": []
  }
]
